clima_nutri/__init__.py
clima_nutri/main.py
clima_nutri/prompts.py
clima_nutri-2025.12.21233357.dist-info/METADATA
clima_nutri-2025.12.21233357.dist-info/WHEEL
clima_nutri-2025.12.21233357.dist-info/top_level.txt
clima_nutri-2025.12.21233357.dist-info/RECORD
