Metadata-Version: 2.4
Name: clima-nutri
Version: 2025.12.21233357
Summary: clima-nutri analyzes text on CO2's impact on food quality, summarizing nutritional and caloric changes for policy and research.
Author-email: clima-nutri <hi@eugene.plus>
License: MIT
Project-URL: Homepage, https://github.com/chigwell/clima-nutri
Requires-Python: >=3.9
Requires-Dist: langchain-llm7>=0.0.0
Requires-Dist: llmatch-messages>=0.0.0
Requires-Dist: langchain-core>=0.3.0
